{
  "timestamp": "2026-06-13T12:15:28.666346",
  "gestation_day": 88,
  "trimester": 1,
  "tags": [
    "heartbeat",
    "trimester_1",
    "day_88"
  ],
  "content": {
    "type": "heartbeat",
    "pulse_count": 60,
    "pulses": [
      {
        "beat": 0,
        "interval": 1.1599,
        "intensity": 0.7952,
        "noise": -0.1509
      },
      {
        "beat": 1,
        "interval": 0.483,
        "intensity": 0.8563,
        "noise": -0.091
      },
      {
        "beat": 2,
        "interval": 1.7999,
        "intensity": 0.8662,
        "noise": -0.1271
      },
      {
        "beat": 3,
        "interval": 1.4072,
        "intensity": 1.0,
        "noise": 0.2952
      },
      {
        "beat": 4,
        "interval": 0.9037,
        "intensity": 0.96,
        "noise": 0.1487
      },
      {
        "beat": 5,
        "interval": 0.8973,
        "intensity": 0.9314,
        "noise": 0.0535
      },
      {
        "beat": 6,
        "interval": 0.9468,
        "intensity": 0.8091,
        "noise": 0.0756
      },
      {
        "beat": 7,
        "interval": 1.3749,
        "intensity": 0.8452,
        "noise": -0.2961
      },
      {
        "beat": 8,
        "interval": 0.6057,
        "intensity": 0.744,
        "noise": 0.1545
      },
      {
        "beat": 9,
        "interval": 1.0943,
        "intensity": 0.6813,
        "noise": 0.0768
      },
      {
        "beat": 10,
        "interval": 1.2015,
        "intensity": 0.7558,
        "noise": -0.0697
      },
      {
        "beat": 11,
        "interval": 0.673,
        "intensity": 0.8144,
        "noise": -0.5793
      },
      {
        "beat": 12,
        "interval": 0.2864,
        "intensity": 0.8844,
        "noise": -0.2674
      },
      {
        "beat": 13,
        "interval": 0.6152,
        "intensity": 0.9601,
        "noise": 0.0895
      },
      {
        "beat": 14,
        "interval": 1.5737,
        "intensity": 0.7778,
        "noise": -0.1603
      },
      {
        "beat": 15,
        "interval": 0.9171,
        "intensity": 0.8822,
        "noise": 0.1319
      },
      {
        "beat": 16,
        "interval": 1.04,
        "intensity": 0.8891,
        "noise": -0.0399
      },
      {
        "beat": 17,
        "interval": 0.624,
        "intensity": 0.947,
        "noise": -0.243
      },
      {
        "beat": 18,
        "interval": 1.4447,
        "intensity": 0.7662,
        "noise": -0.075
      },
      {
        "beat": 19,
        "interval": 0.3066,
        "intensity": 0.7741,
        "noise": 0.324
      },
      {
        "beat": 20,
        "interval": 0.3323,
        "intensity": 0.9191,
        "noise": 0.2126
      },
      {
        "beat": 21,
        "interval": 0.417,
        "intensity": 0.9243,
        "noise": 0.0786
      },
      {
        "beat": 22,
        "interval": 1.1154,
        "intensity": 0.7876,
        "noise": -0.2829
      },
      {
        "beat": 23,
        "interval": 0.2552,
        "intensity": 0.9074,
        "noise": 0.3589
      },
      {
        "beat": 24,
        "interval": 0.8636,
        "intensity": 0.7648,
        "noise": 0.1255
      },
      {
        "beat": 25,
        "interval": 1.8475,
        "intensity": 0.8122,
        "noise": 0.0159
      },
      {
        "beat": 26,
        "interval": 1.3707,
        "intensity": 0.8607,
        "noise": 0.4184
      },
      {
        "beat": 27,
        "interval": 0.9745,
        "intensity": 0.6549,
        "noise": -0.5543
      },
      {
        "beat": 28,
        "interval": 0.9862,
        "intensity": 0.7753,
        "noise": 0.0571
      },
      {
        "beat": 29,
        "interval": 0.5716,
        "intensity": 0.9033,
        "noise": -0.166
      },
      {
        "beat": 30,
        "interval": 1.6477,
        "intensity": 0.9818,
        "noise": 0.1339
      },
      {
        "beat": 31,
        "interval": 1.2914,
        "intensity": 0.7397,
        "noise": -0.1908
      },
      {
        "beat": 32,
        "interval": 0.7653,
        "intensity": 0.9013,
        "noise": -0.279
      },
      {
        "beat": 33,
        "interval": 1.4179,
        "intensity": 0.73,
        "noise": 0.2627
      },
      {
        "beat": 34,
        "interval": 0.7056,
        "intensity": 0.9638,
        "noise": 0.2402
      },
      {
        "beat": 35,
        "interval": 1.3931,
        "intensity": 0.8036,
        "noise": 0.2077
      },
      {
        "beat": 36,
        "interval": 0.4011,
        "intensity": 0.7682,
        "noise": -0.1136
      },
      {
        "beat": 37,
        "interval": 0.4657,
        "intensity": 0.929,
        "noise": -0.1517
      },
      {
        "beat": 38,
        "interval": 0.9243,
        "intensity": 0.8733,
        "noise": 0.0241
      },
      {
        "beat": 39,
        "interval": 0.8062,
        "intensity": 0.8089,
        "noise": -0.0344
      },
      {
        "beat": 40,
        "interval": 0.8136,
        "intensity": 0.8857,
        "noise": -0.1656
      },
      {
        "beat": 41,
        "interval": 1.7169,
        "intensity": 0.9031,
        "noise": -0.0943
      },
      {
        "beat": 42,
        "interval": 1.5943,
        "intensity": 0.7791,
        "noise": 0.253
      },
      {
        "beat": 43,
        "interval": 0.6883,
        "intensity": 0.9105,
        "noise": 0.0485
      },
      {
        "beat": 44,
        "interval": 0.5885,
        "intensity": 0.8781,
        "noise": 0.5198
      },
      {
        "beat": 45,
        "interval": 1.2631,
        "intensity": 0.7582,
        "noise": 0.0797
      },
      {
        "beat": 46,
        "interval": 1.0034,
        "intensity": 0.8167,
        "noise": 0.1787
      },
      {
        "beat": 47,
        "interval": 1.5841,
        "intensity": 0.7691,
        "noise": 0.0203
      },
      {
        "beat": 48,
        "interval": 1.3917,
        "intensity": 1.0,
        "noise": 0.031
      },
      {
        "beat": 49,
        "interval": 0.8775,
        "intensity": 0.9431,
        "noise": -0.2424
      },
      {
        "beat": 50,
        "interval": 0.5952,
        "intensity": 0.6628,
        "noise": 0.3109
      },
      {
        "beat": 51,
        "interval": 1.4082,
        "intensity": 0.8486,
        "noise": -0.6
      },
      {
        "beat": 52,
        "interval": 1.5611,
        "intensity": 0.8733,
        "noise": 0.0698
      },
      {
        "beat": 53,
        "interval": 1.2814,
        "intensity": 0.8172,
        "noise": 0.3064
      },
      {
        "beat": 54,
        "interval": 1.5393,
        "intensity": 0.7617,
        "noise": -0.2122
      },
      {
        "beat": 55,
        "interval": 0.7217,
        "intensity": 0.8444,
        "noise": 0.3168
      },
      {
        "beat": 56,
        "interval": 1.5228,
        "intensity": 0.6889,
        "noise": -0.2984
      },
      {
        "beat": 57,
        "interval": 0.2452,
        "intensity": 0.8886,
        "noise": 0.0756
      },
      {
        "beat": 58,
        "interval": 0.2791,
        "intensity": 0.937,
        "noise": 0.366
      },
      {
        "beat": 59,
        "interval": 1.0683,
        "intensity": 0.728,
        "noise": 0.0601
      }
    ],
    "womb": {
      "heartbeat_bpm": 80,
      "rhythm_type": "arrhythmic",
      "cortisol_level": 0.7,
      "entropy_level": 0.9
    },
    "maternal_drivers": {
      "arousal": 1.0,
      "stress": 0.0,
      "recovery": 1.0,
      "present": false
    },
    "maternal_signal_date": null
  }
}