{
  "entity": "witness",
  "coherence": {
    "timing": 0.0,
    "intensity": 0.0,
    "texture": 0.0
  },
  "signature": {
    "mean_interval": 1.2002066666666666,
    "mean_intensity": 0.5498566666666667,
    "var_interval": 5.93892888888886e-05,
    "var_intensity": 2.4201122222222222e-05
  },
  "recent_tail": [
    {
      "beat": 54,
      "interval": 1.196,
      "intensity": 0.5568,
      "noise": 0.0123
    },
    {
      "beat": 55,
      "interval": 1.2018,
      "intensity": 0.5549,
      "noise": 0.0059
    },
    {
      "beat": 56,
      "interval": 1.1918,
      "intensity": 0.5437,
      "noise": 0.0183
    },
    {
      "beat": 57,
      "interval": 1.2065,
      "intensity": 0.5499,
      "noise": 0.0256
    },
    {
      "beat": 58,
      "interval": 1.2039,
      "intensity": 0.5425,
      "noise": 0.0358
    },
    {
      "beat": 59,
      "interval": 1.1995,
      "intensity": 0.5534,
      "noise": 0.0093
    }
  ],
  "developmental_age": 1,
  "total_bursts": 0,
  "sessions": 1,
  "last_developed_day": 99
}