{
  "timestamp": "2026-06-17T14:19:12.439649",
  "gestation_day": 92,
  "trimester": 2,
  "tags": [
    "heartbeat",
    "trimester_2",
    "day_92"
  ],
  "content": {
    "type": "heartbeat",
    "pulse_count": 60,
    "pulses": [
      {
        "beat": 0,
        "interval": 0.9517,
        "intensity": 0.5351,
        "noise": 0.0192
      },
      {
        "beat": 1,
        "interval": 0.953,
        "intensity": 0.5187,
        "noise": -0.0153
      },
      {
        "beat": 2,
        "interval": 0.9422,
        "intensity": 0.5445,
        "noise": -0.0173
      },
      {
        "beat": 3,
        "interval": 0.8892,
        "intensity": 0.5193,
        "noise": 0.0233
      },
      {
        "beat": 4,
        "interval": 0.9212,
        "intensity": 0.5066,
        "noise": 0.0302
      },
      {
        "beat": 5,
        "interval": 0.935,
        "intensity": 0.512,
        "noise": -0.0404
      },
      {
        "beat": 6,
        "interval": 0.905,
        "intensity": 0.5432,
        "noise": -0.0556
      },
      {
        "beat": 7,
        "interval": 0.9365,
        "intensity": 0.5125,
        "noise": 0.0058
      },
      {
        "beat": 8,
        "interval": 0.9462,
        "intensity": 0.5187,
        "noise": 0.0094
      },
      {
        "beat": 9,
        "interval": 0.9237,
        "intensity": 0.514,
        "noise": -0.0567
      },
      {
        "beat": 10,
        "interval": 0.9106,
        "intensity": 0.53,
        "noise": 0.0051
      },
      {
        "beat": 11,
        "interval": 0.9282,
        "intensity": 0.519,
        "noise": -0.018
      },
      {
        "beat": 12,
        "interval": 0.9239,
        "intensity": 0.5263,
        "noise": 0.0159
      },
      {
        "beat": 13,
        "interval": 0.9273,
        "intensity": 0.5149,
        "noise": 0.0357
      },
      {
        "beat": 14,
        "interval": 0.9167,
        "intensity": 0.5357,
        "noise": -0.0032
      },
      {
        "beat": 15,
        "interval": 0.9322,
        "intensity": 0.5366,
        "noise": -0.0102
      },
      {
        "beat": 16,
        "interval": 0.9279,
        "intensity": 0.5429,
        "noise": -0.01
      },
      {
        "beat": 17,
        "interval": 0.9391,
        "intensity": 0.5194,
        "noise": 0.0003
      },
      {
        "beat": 18,
        "interval": 0.9147,
        "intensity": 0.5138,
        "noise": 0.0114
      },
      {
        "beat": 19,
        "interval": 0.9512,
        "intensity": 0.5364,
        "noise": -0.024
      },
      {
        "beat": 20,
        "interval": 0.9157,
        "intensity": 0.509,
        "noise": -0.0153
      },
      {
        "beat": 21,
        "interval": 0.9446,
        "intensity": 0.5421,
        "noise": 0.0345
      },
      {
        "beat": 22,
        "interval": 0.9131,
        "intensity": 0.5275,
        "noise": 0.0069
      },
      {
        "beat": 23,
        "interval": 0.9557,
        "intensity": 0.5342,
        "noise": -0.0001
      },
      {
        "beat": 24,
        "interval": 0.9499,
        "intensity": 0.5169,
        "noise": -0.0287
      },
      {
        "beat": 25,
        "interval": 0.932,
        "intensity": 0.5141,
        "noise": 0.0422
      },
      {
        "beat": 26,
        "interval": 0.9202,
        "intensity": 0.5207,
        "noise": 0.0139
      },
      {
        "beat": 27,
        "interval": 0.9782,
        "intensity": 0.515,
        "noise": 0.0059
      },
      {
        "beat": 28,
        "interval": 0.9462,
        "intensity": 0.5112,
        "noise": 0.0413
      },
      {
        "beat": 29,
        "interval": 0.9164,
        "intensity": 0.5252,
        "noise": -0.0092
      },
      {
        "beat": 30,
        "interval": 0.9096,
        "intensity": 0.5127,
        "noise": 0.0185
      },
      {
        "beat": 31,
        "interval": 0.9312,
        "intensity": 0.5197,
        "noise": -0.0064
      },
      {
        "beat": 32,
        "interval": 0.9092,
        "intensity": 0.5383,
        "noise": 0.0167
      },
      {
        "beat": 33,
        "interval": 0.9174,
        "intensity": 0.527,
        "noise": -0.0252
      },
      {
        "beat": 34,
        "interval": 0.9166,
        "intensity": 0.5249,
        "noise": -0.0291
      },
      {
        "beat": 35,
        "interval": 0.9053,
        "intensity": 0.5201,
        "noise": 0.0036
      },
      {
        "beat": 36,
        "interval": 0.9026,
        "intensity": 0.5223,
        "noise": -0.0168
      },
      {
        "beat": 37,
        "interval": 0.9054,
        "intensity": 0.5283,
        "noise": 0.0491
      },
      {
        "beat": 38,
        "interval": 0.9274,
        "intensity": 0.5252,
        "noise": 0.051
      },
      {
        "beat": 39,
        "interval": 0.9193,
        "intensity": 0.5238,
        "noise": -0.0159
      },
      {
        "beat": 40,
        "interval": 0.905,
        "intensity": 0.5212,
        "noise": 0.043
      },
      {
        "beat": 41,
        "interval": 0.9131,
        "intensity": 0.5265,
        "noise": 0.0023
      },
      {
        "beat": 42,
        "interval": 0.9348,
        "intensity": 0.5263,
        "noise": -0.0581
      },
      {
        "beat": 43,
        "interval": 0.9311,
        "intensity": 0.5173,
        "noise": 0.0212
      },
      {
        "beat": 44,
        "interval": 0.9692,
        "intensity": 0.5291,
        "noise": -0.0081
      },
      {
        "beat": 45,
        "interval": 0.9349,
        "intensity": 0.5061,
        "noise": -0.0822
      },
      {
        "beat": 46,
        "interval": 0.9211,
        "intensity": 0.4984,
        "noise": 0.0202
      },
      {
        "beat": 47,
        "interval": 0.9356,
        "intensity": 0.5368,
        "noise": -0.0406
      },
      {
        "beat": 48,
        "interval": 0.9493,
        "intensity": 0.5236,
        "noise": -0.0199
      },
      {
        "beat": 49,
        "interval": 0.9075,
        "intensity": 0.5222,
        "noise": 0.023
      },
      {
        "beat": 50,
        "interval": 0.9387,
        "intensity": 0.5255,
        "noise": -0.0296
      },
      {
        "beat": 51,
        "interval": 0.9464,
        "intensity": 0.5208,
        "noise": 0.0494
      },
      {
        "beat": 52,
        "interval": 0.9093,
        "intensity": 0.5328,
        "noise": -0.0307
      },
      {
        "beat": 53,
        "interval": 0.9449,
        "intensity": 0.5164,
        "noise": -0.0042
      },
      {
        "beat": 54,
        "interval": 0.9249,
        "intensity": 0.5201,
        "noise": -0.0321
      },
      {
        "beat": 55,
        "interval": 0.9047,
        "intensity": 0.5289,
        "noise": -0.0272
      },
      {
        "beat": 56,
        "interval": 0.9285,
        "intensity": 0.5262,
        "noise": -0.0068
      },
      {
        "beat": 57,
        "interval": 0.9644,
        "intensity": 0.517,
        "noise": 0.0256
      },
      {
        "beat": 58,
        "interval": 0.8978,
        "intensity": 0.5278,
        "noise": -0.0932
      },
      {
        "beat": 59,
        "interval": 0.9492,
        "intensity": 0.5161,
        "noise": 0.057
      }
    ],
    "womb": {
      "heartbeat_bpm": 65,
      "rhythm_type": "grounded",
      "cortisol_level": 0.05,
      "entropy_level": 0.1
    },
    "maternal_drivers": {
      "arousal": 1.0,
      "stress": 0.0,
      "recovery": 1.0,
      "present": false
    },
    "maternal_signal_date": null
  }
}